Metadata-Version: 1.1
Name: LibraryH
Version: 0.1.0
Summary: give you a better experience
Home-page: https://pypi.org
Author: zjy_090820
Author-email: a1234567890001919@outlook.com
License: UNKNOWN
Platform: UNKNOWN
Classifier: Programming Language :: Python :: 3
Classifier: License :: OSI Approved :: MIT License
Classifier: Operating System :: OS Independent
